pyonlinesvr/__init__.py
pyonlinesvr/_version.py
pyonlinesvr/osvr.py
pyonlinesvr/py.typed
pyonlinesvr/lib/__init__.py
pyonlinesvr/lib/_onlinesvr.cp39-win_amd64.pyd
pyonlinesvr/lib/compat.py
pyonlinesvr/lib/onlinesvr.py
tests/__init__.py
tests/test_osvr.py
tests/lib/__init__.py
tests/lib/test_compat.py
PyOnlineSVR-0.0.4.dist-info/LICENSE
PyOnlineSVR-0.0.4.dist-info/METADATA
PyOnlineSVR-0.0.4.dist-info/WHEEL
PyOnlineSVR-0.0.4.dist-info/top_level.txt
PyOnlineSVR-0.0.4.dist-info/RECORD
