Metadata-Version: 2.1
Name: PyOnlineSVR
Version: 0.0.4
Summary: Python-Wrapper for Francesco Parrella's OnlineSVR C++ implementation.
Home-page: https://github.com/CodeLionX/pyonlinesvr
Download-URL: https://github.com/CodeLionX/pyonlinesvr
Author: Sebastian Schmidl
Author-email: info@sebastianschmidl.de
License: GPLv3
Classifier: Development Status :: 3 - Alpha
Classifier: Intended Audience :: Science/Research
Classifier: Intended Audience :: Developers
Classifier: License :: OSI Approved :: GNU General Public License v3 or later (GPLv3+)
Classifier: Programming Language :: Python
Classifier: Topic :: Software Development
Classifier: Topic :: Scientific/Engineering
Classifier: Operating System :: Unix
Classifier: Operating System :: POSIX :: Linux
Classifier: Programming Language :: C++
Classifier: Programming Language :: Python :: 3.7
Classifier: Programming Language :: Python :: 3.8
Classifier: Programming Language :: Python :: 3.9
Classifier: Programming Language :: Python :: 3.10
Classifier: Typing :: Typed
Requires-Python: >=3.7
Provides-Extra: test
Provides-Extra: doc
License-File: LICENSE
